<?xml version="1.0" encoding="UTF-8"?>
<beans xmlns:xsi="http://www.w3.org/2001/XMLSchema-instance"
       xmlns:context="http://www.springframework.org/schema/context"
       xmlns:util="http://www.springframework.org/schema/util"
       xmlns="http://www.springframework.org/schema/beans"
       xsi:schemaLocation="http://www.springframework.org/schema/beans http://www.springframework.org/schema/beans/spring-beans-3.0.xsd
		http://www.springframework.org/schema/context http://www.springframework.org/schema/context/spring-context-3.0.xsd
		  http://www.springframework.org/schema/util http://www.springframework.org/schema/util/spring-util.xsd">


    <context:property-placeholder location="file:/var/local/ida/upload.properties"/>

    <!-- Solr -->
    <bean id="defaultSolrUpdater" class="de.idadachverband.solr.SolrService">
        <constructor-arg index="0" value="Metadev"/>
        <constructor-arg index="1" value="${solr.url}"/>
    </bean>
    <bean id="genderbibSolrUpdater" class="de.idadachverband.solr.SolrService">
        <constructor-arg index="0" value="Genderbib"/>
        <constructor-arg index="1" value="${solr.url.genderbib}"/>
    </bean>

    <util:set id="solrServiceSet" set-class="java.util.HashSet" value-type="de.idadachverband.solr.SolrService">
        <ref bean="defaultSolrUpdater"/>
        <ref bean="genderbibSolrUpdater"/>
    </util:set>

    <!-- XSLT -->
    <bean id="genderbib" class="de.idadachverband.institution.IdaInstitutionBean">
        <constructor-arg index="0" name="institutionName" value="Genderbibliothek"/>
        <constructor-arg index="1" name="transformationRecipeFile"
                         value="${xslt.basePath}/institution/genderbib/gleich_genderbib.xsl"/>
        <constructor-arg index="2" name="transformationStrategy" ref="xsltTransformer"/>
        <property name="incrementalUpdateAllowed" value="true"/>
    </bean>
    <bean id="frauenmediaturm" class="de.idadachverband.institution.IdaInstitutionBean">
        <constructor-arg index="0" name="institutionName" value="FrauenMediaTurm"/>
        <constructor-arg index="1" name="transformationRecipeFile"
                         value="${xslt.basePath}/institution/fmt/gleich_fmt.xsl"/>
        <constructor-arg index="2" name="transformationStrategy" ref="xsltTransformer"/>
        <property name="incrementalUpdateAllowed" value="true"/>
    </bean>
    <bean id="frauensolidaritaet" class="de.idadachverband.institution.IdaInstitutionBean">
        <constructor-arg index="0" name="institutionName" value="Frauensolidaritaet"/>
        <constructor-arg index="1" name="transformationRecipeFile"
                         value="${xslt.basePath}/institution/frauensolidaritaet/gleich_frauensolidaritaet.xsl"/>
        <constructor-arg index="2" name="transformationStrategy" ref="xsltTransformer"/>
        <property name="incrementalUpdateAllowed" value="true"/>
    </bean>
    <bean id="ffbiz" class="de.idadachverband.institution.IdaInstitutionBean">
        <constructor-arg index="0" name="institutionName" value="FFBIZ-Archiv"/>
        <constructor-arg index="1" name="transformationRecipeFile"
                         value="${xslt.basePath}/institution/ffbiz/gleich_ffbiz.xsl"/>
        <constructor-arg index="2" name="transformationStrategy" ref="xsltTransformer"/>
        <property name="incrementalUpdateAllowed" value="true"/>
    </bean>
    <bean id="belladonna" class="de.idadachverband.institution.IdaInstitutionBean">
        <constructor-arg index="0" name="institutionName" value="belladonna"/>
        <constructor-arg index="1" name="transformationRecipeFile"
                         value="${xslt.basePath}/institution/belladonna/gleich_belladonna.xsl"/>
        <constructor-arg index="2" name="transformationStrategy" ref="xsltTransformer"/>
        <property name="incrementalUpdateAllowed" value="true"/>
    </bean>
    <bean id="spinnboden" class="de.idadachverband.institution.IdaInstitutionBean">
        <constructor-arg index="0" name="institutionName" value="spinnboden"/>
        <constructor-arg index="1" name="transformationRecipeFile"
                         value="${xslt.basePath}/institution/spinnboden/gleich_spibo.xsl"/>
        <constructor-arg index="2" name="transformationStrategy" ref="xsltTransformer"/>
        <property name="incrementalUpdateAllowed" value="true"/>
    </bean>
    <bean id="stichwort" class="de.idadachverband.institution.IdaInstitutionBean">
        <constructor-arg index="0" name="institutionName" value="stichwort"/>
        <constructor-arg index="1" name="transformationRecipeFile"
                         value="${xslt.basePath}/institution/stichwort/gleich_stichwort.xsl"/>
        <constructor-arg index="2" name="transformationStrategy" ref="xsltTransformer"/>
        <property name="incrementalUpdateAllowed" value="true"/>
    </bean>
    <bean id="ash" class="de.idadachverband.institution.IdaInstitutionBean">
        <constructor-arg index="0" name="institutionName" value="AliceSalomonArchiv"/>
        <constructor-arg index="1" name="transformationRecipeFile"
                         value="${xslt.basePath}/institution/ash/gleich_ash.xsl"/>
        <constructor-arg index="2" name="transformationStrategy" ref="xsltTransformer"/>
        <property name="incrementalUpdateAllowed" value="true"/>
    </bean>
    <bean id="cid" class="de.idadachverband.institution.IdaInstitutionBean">
        <constructor-arg index="0" name="institutionName" value="CidFraenanGender"/>
        <constructor-arg index="1" name="transformationRecipeFile"
                         value="${xslt.basePath}/institution/cid/gleich_cid.xsl"/>
        <constructor-arg index="2" name="transformationStrategy" ref="xsltTransformer"/>
        <property name="incrementalUpdateAllowed" value="true"/>
    </bean>
     <bean id="schemaf" class="de.idadachverband.institution.IdaInstitutionBean">
        <constructor-arg index="0" name="institutionName" value="Schemaf"/>
        <constructor-arg index="1" name="transformationRecipeFile"
                         value="${xslt.basePath}/institution/schemaf/gleich_schemaf.xsl"/>
        <constructor-arg index="2" name="transformationStrategy" ref="xsltTransformer"/>
        <property name="incrementalUpdateAllowed" value="true"/>
    </bean>
     <bean id="helenelange" class="de.idadachverband.institution.IdaInstitutionBean">
        <constructor-arg index="0" name="institutionName" value="Helene Lange Archiv"/>
        <constructor-arg index="1" name="transformationRecipeFile"
                         value="${xslt.basePath}/institution/hla/gleich_hla.xsl"/>
        <constructor-arg index="2" name="transformationStrategy" ref="xsltTransformer"/>
        <property name="incrementalUpdateAllowed" value="true"/>
    </bean>
    
    <util:set id="institutionsSet" set-class="java.util.HashSet"
              value-type="de.idadachverband.institution.IdaInstitutionBean">
        <ref bean="genderbib"/>
        <ref bean="frauenmediaturm"/>
        <ref bean="frauensolidaritaet"/>
        <ref bean="ffbiz"/>
        <ref bean="belladonna"/>
        <ref bean="spinnboden"/>
        <ref bean="stichwort"/>
    </util:set>

    <bean id="workingFormatTransformer" class="de.idadachverband.transform.xslt.WorkingFormatToSolrDocumentTransformer"
          scope="prototype">
        <constructor-arg name="gleichXsl" value="${xslt.basePath}/data/2bibxml.xsl"/>
    </bean>

    <bean id="mailSender" class="org.springframework.mail.javamail.JavaMailSenderImpl">
        <!-- SMTP settings -->
        <property name="host" value="${smtp.host}"/>
        <property name="port" value="${smtp.port}"/>
        <property name="username" value="${smtp.username}"/>
        <property name="password" value="${smtp.password}"/>


        <property name="javaMailProperties">
            <!-- additional properties specific to JavaMail -->
            <props>
                <prop key="mail.transport.protocol">smtp</prop>
                <prop key="mail.smtp.auth">${smtp.auth}</prop>
                <prop key="mail.smtp.starttls.enable">${smtp.starttls}</prop>
            </props>
        </property>
    </bean>

    <bean id="archivePath" class="java.nio.file.Paths" factory-method="get">
        <constructor-arg value="file:/var/local/ida/archive"/>
    </bean>

    <bean id="processBasePath" class="java.nio.file.Paths" factory-method="get">
        <constructor-arg value="file:/var/local/ida/processing"/>
    </bean>

    <bean id="uploadPath" class="java.nio.file.Paths" factory-method="get">
        <constructor-arg value="file:/tmp/ida/"/>
    </bean>

    <bean id="dateFormat" class="java.text.SimpleDateFormat">
        <constructor-arg value="yyyyMMdd_HHmmss"/>
    </bean>
    
    <bean id="maxArchivedVersions" class="java.lang.Integer">
    	<constructor-arg value="2"/>
    </bean>
</beans>